{
  "@context": "https://www.w3.org/2019/wot/td/v1",
  "@type": "tm:ThingModel",
  "@id": "dtmi:digitaltwins:aas:Operation;1",
  "description": "An operation is a submodel element with input and output variables",
  "title": "Operation",
  "$comment": "According Platform Industrie 4.0. Details of Asset Administration Shell (Version 3.0) Part 1 Release Candidate 02",
  "created": "2024-01-17T15:53:51.2745227+01:00",
  "modified": "2024-01-17T15:53:51.2745252+01:00",
  "links": [
    {
      "href": "dtmi:digitaltwins:aas:OperationVariable;1",
      "rel": "dtdl:inputVariable",
      "@type": "dtdl:Relationship",
      "dtdl:displayName": "Input variable",
      "dtdl:description": "Input parameter of the operation.",
      "dtdl:writable": true
    },
    {
      "href": "dtmi:digitaltwins:aas:OperationVariable;1",
      "rel": "dtdl:outputVariable",
      "@type": "dtdl:Relationship",
      "dtdl:displayName": "Output variable",
      "dtdl:description": "Output parameter of the operation.",
      "dtdl:writable": true
    },
    {
      "href": "dtmi:digitaltwins:aas:OperationVariable;1",
      "rel": "dtdl:inoutputVariable",
      "@type": "dtdl:Relationship",
      "dtdl:displayName": "Input and output variable",
      "dtdl:description": "Parameter that is input and output of the operation.",
      "dtdl:writable": true
    },
    {
      "href": "dtmi:digitaltwins:aas:SubmodelElement;1",
      "rel": "tm:extends"
    }
  ]
}